stdpopsim/__init__.py
stdpopsim/__main__.py
stdpopsim/_version.py
stdpopsim/annotations.py
stdpopsim/cache.py
stdpopsim/citations.py
stdpopsim/cli.py
stdpopsim/dfe.py
stdpopsim/engines.py
stdpopsim/genetic_maps.py
stdpopsim/genomes.py
stdpopsim/models.py
stdpopsim/selection.py
stdpopsim/slim_engine.py
stdpopsim/species.py
stdpopsim/utils.py
stdpopsim/warning_categories.py
stdpopsim/catalog/__init__.py
stdpopsim/catalog/AedAeg/__init__.py
stdpopsim/catalog/AedAeg/genome_data.py
stdpopsim/catalog/AedAeg/species.py
stdpopsim/catalog/AnaPla/__init__.py
stdpopsim/catalog/AnaPla/demographic_models.py
stdpopsim/catalog/AnaPla/genome_data.py
stdpopsim/catalog/AnaPla/species.py
stdpopsim/catalog/AnoCar/__init__.py
stdpopsim/catalog/AnoCar/genome_data.py
stdpopsim/catalog/AnoCar/species.py
stdpopsim/catalog/AnoGam/__init__.py
stdpopsim/catalog/AnoGam/demographic_models.py
stdpopsim/catalog/AnoGam/genome_data.py
stdpopsim/catalog/AnoGam/species.py
stdpopsim/catalog/ApiMel/__init__.py
stdpopsim/catalog/ApiMel/genome_data.py
stdpopsim/catalog/ApiMel/species.py
stdpopsim/catalog/AraTha/__init__.py
stdpopsim/catalog/AraTha/annotations.py
stdpopsim/catalog/AraTha/demographic_models.py
stdpopsim/catalog/AraTha/dfes.py
stdpopsim/catalog/AraTha/genetic_maps.py
stdpopsim/catalog/AraTha/genome_data.py
stdpopsim/catalog/AraTha/species.py
stdpopsim/catalog/BosTau/__init__.py
stdpopsim/catalog/BosTau/demographic_models.py
stdpopsim/catalog/BosTau/genome_data.py
stdpopsim/catalog/BosTau/species.py
stdpopsim/catalog/CaeEle/__init__.py
stdpopsim/catalog/CaeEle/genetic_maps.py
stdpopsim/catalog/CaeEle/genome_data.py
stdpopsim/catalog/CaeEle/species.py
stdpopsim/catalog/CanFam/__init__.py
stdpopsim/catalog/CanFam/demographic_models.py
stdpopsim/catalog/CanFam/genetic_maps.py
stdpopsim/catalog/CanFam/genome_data.py
stdpopsim/catalog/CanFam/species.py
stdpopsim/catalog/ChlRei/__init__.py
stdpopsim/catalog/ChlRei/genome_data.py
stdpopsim/catalog/ChlRei/species.py
stdpopsim-0.3.0.dist-info/LICENSE
stdpopsim-0.3.0.dist-info/METADATA
stdpopsim-0.3.0.dist-info/WHEEL
stdpopsim-0.3.0.dist-info/entry_points.txt
stdpopsim-0.3.0.dist-info/top_level.txt
stdpopsim-0.3.0.dist-info/RECORD
